pytket/qir/__init__.py
pytket/qir/_metadata.py
pytket/qir/py.typed
pytket/qir/conversion/__init__.py
pytket/qir/conversion/api.py
pytket/qir/conversion/azurebaseprofileqirgenerator.py
pytket/qir/conversion/azureprofileqirgenerator.py
pytket/qir/conversion/baseprofileqirgenerator.py
pytket/qir/conversion/gatesets.py
pytket/qir/conversion/module.py
pytket/qir/conversion/profileqirgenerator.py
pytket/qir/conversion/pytketqirgenerator.py
pytket/qir/conversion/qirgenerator.py
pytket_qir-0.25.0.dist-info/licenses/LICENSE
pytket_qir-0.25.0.dist-info/METADATA
pytket_qir-0.25.0.dist-info/WHEEL
pytket_qir-0.25.0.dist-info/top_level.txt
pytket_qir-0.25.0.dist-info/RECORD
