Metadata-Version: 2.4
Name: pytket-qir
Version: 0.25.0
Summary: Extension for pytket, providing functions for conversion into to qir
Author: TKET development team
Author-email: tket-support@quantinuum.com
License: Apache 2
Project-URL: Documentation, https://tket.quantinuum.com/extensions/pytket-qir/index.html
Project-URL: Source, https://github.com/CQCL/pytket-qir
Project-URL: Tracker, https://github.com/CQCL/pytket-qir/issues
Classifier: Environment :: Console
Classifier: Programming Language :: Python :: 3.10
Classifier: Programming Language :: Python :: 3.11
Classifier: Programming Language :: Python :: 3.12
Classifier: Programming Language :: Python :: 3.13
Classifier: License :: OSI Approved :: Apache Software License
Classifier: Operating System :: MacOS :: MacOS X
Classifier: Operating System :: POSIX :: Linux
Classifier: Operating System :: Microsoft :: Windows
Classifier: Intended Audience :: Developers
Classifier: Intended Audience :: Science/Research
Classifier: Topic :: Scientific/Engineering
Requires-Python: >=3.10
License-File: LICENSE
Requires-Dist: pytket>=2.9.3
Requires-Dist: pyqir~=0.10.9
Dynamic: author
Dynamic: author-email
Dynamic: classifier
Dynamic: description
Dynamic: description-content-type
Dynamic: license
Dynamic: license-file
Dynamic: project-url
Dynamic: requires-dist
Dynamic: requires-python
Dynamic: summary
